broh5/__init__.py
broh5/main.py
broh5/lib/__init__.py
broh5/lib/interactions.py
broh5/lib/rendering.py
broh5/lib/utilities.py
broh5-1.4.2.dist-info/licenses/LICENSE
broh5-1.4.2.dist-info/METADATA
broh5-1.4.2.dist-info/WHEEL
broh5-1.4.2.dist-info/entry_points.txt
broh5-1.4.2.dist-info/top_level.txt
broh5-1.4.2.dist-info/RECORD
