Metadata-Version: 2.4
Name: broh5
Version: 1.4.2
Summary: Browser-based GUI HDF Viewer in Python
Home-page: https://github.com/algotom/broh5
Download-URL: https://github.com/algotom/broh5.git
Author: Nghia Vo
Author-email: nvo@bnl.gov
License: Apache 2.0
Keywords: HDF Viewer,NXS Viewer,Browser-based GUI
Platform: Any
Classifier: Programming Language :: Python :: 3
Classifier: License :: OSI Approved :: Apache Software License
Classifier: Intended Audience :: Science/Research
Classifier: Operating System :: OS Independent
Classifier: Natural Language :: English
Classifier: Topic :: Scientific/Engineering
Requires-Python: >=3.9
License-File: LICENSE
Requires-Dist: numpy>=1.23
Requires-Dist: h5py>3.7
Requires-Dist: hdf5plugin
Requires-Dist: pillow
Requires-Dist: matplotlib
Requires-Dist: nicegui>=3.0
Dynamic: author
Dynamic: author-email
Dynamic: classifier
Dynamic: description
Dynamic: description-content-type
Dynamic: download-url
Dynamic: home-page
Dynamic: keywords
Dynamic: license
Dynamic: license-file
Dynamic: platform
Dynamic: requires-dist
Dynamic: requires-python
Dynamic: summary
